mypackage/__init__.py
tmw-0.0.0.dist-info/METADATA
tmw-0.0.0.dist-info/WHEEL
tmw-0.0.0.dist-info/entry_points.txt
tmw-0.0.0.dist-info/top_level.txt
tmw-0.0.0.dist-info/RECORD
